numerosprimos/__init__.py
numerosprimos-1.0.dist-info/LICENSE.txt
numerosprimos-1.0.dist-info/METADATA
numerosprimos-1.0.dist-info/WHEEL
numerosprimos-1.0.dist-info/top_level.txt
numerosprimos-1.0.dist-info/RECORD
