Metadata-Version: 2.1
Name: numerosprimos
Version: 1.0
Summary: An awesome package that calculate prime numbers
Home-page: UNKNOWN
Author: Fatima Amou
Author-email: amoufatimazahra@gmail.com
License: GNU GPLv3
Platform: UNKNOWN
Classifier: Development Status :: 4 - Beta
Classifier: Intended Audience :: Developers
Classifier: License :: OSI Approved :: GNU General Public License v3 (GPLv3)
Classifier: Operating System :: OS Independent
Classifier: Programming Language :: Python :: 3
